[
    {
        "title": "[오후의 쟁점] 침체의 끝? '메모리 반도체' / '업턴'의 시작? '게임'",
        "newstext": "\n\n\n\n출연>\n\n원상준 유안타증권 인천지점 차장\n\n이화진 하이투자증권 스마트PB센터 과장\n\n\n\n▶쟁점#1 : 메모리 반도체\n\n\"낸드 가격 인상, 빨라지는 반도체의 봄?\"\n\n\n\n반도체주 탑픽 : 티엘비\n\n\n\n\n\n▶쟁점#2 : 게임\n\n\"위메이드 역대급 실적, 부활의 신호탄?\"\n\n\n\n게임주 탑픽 : 위메이드\n\n\n\n\n\n▶쟁점#3 : 여행주\n\n\"날아오른 실적, 주가도 턴어라운드?\"\n\n\n\nQ. 하나투어, 3분기 '깜짝 실적'… 주가도 턴어라운드?\n\nQ. 여행주, 장기 하락으로 쌓인 '대기매물'… 투자전략은?\n\nQ. '달리는 말' 여행주 vs '날개 꺾인' 항공주… 탑픽은?\n\n\n\n\n\n\n\n※ 이 방송은 매일 12시 ~ 13시 20분에 LIVE로 시청하실 수 있습니다.\n\n방송 종료 후에는 유튜브 또는 인터넷 다시보기로 시청하실 수 있습니다.\n\n\n\n시청 방법\n\n▶ 유튜브 MTN 머니투데이방송 공식 채널 (☞ MTN 또는 머니투데이방송 검색)\n\n▶ 케이블TV (Btv 152번, 올레tv 181번, U+tv 163번, 스카이라이프 92번)\n\n▶ WAVE, 카카오TV, NAVER TV, 아프리카TV, ZUM TV\n\n▶ 머니투데이방송 홈페이지\n\n",
        "summary": "게임주 탑픽 : 위메이드▶쟁점#3 : 여행주\"날아오른 실적, 주가도 턴어라운드?\"\n하나투어, 3분기 '깜짝 실적'… 주가도 턴어라운드?\n※ 이 방송은 매일 12시 ~ 13시 20분에 LIVE로 시청하실 수 있습니다.\n방송 종료 후에는 유튜브 또는 인터넷 다시보기로 시청하실 수 있습니다.\n시청 방법▶ 유튜브 MTN 머니투데이방송 공식 채널 (☞ MTN 또는 머니투데이방송 검색)▶ 케이블TV (Btv 152번, 올레tv 181번, U+tv 163번, 스카이라이프 92번)▶ WAVE, 카카오TV, NAVER TV, 아프리카TV, ZUM TV▶ 머니투데이방송 홈페이지",
        "gentime": "2023-11-08T13:37:54.000Z",
        "img": "https://cdn.mtn.co.kr/2023/11/08/20231108_time_04_csy_1.jpg",
        "link": "https://news.mtn.co.kr/news-detail/2023110813361140904",
        "companytag": "none",
        "imagelist": "none",
        "keywords": [
            "쟁점",
            "머니투데이방송",
            "실적",
            "오후의",
            "업턴의",
            "메모리",
            "여행주",
            "턴어라운드q",
            "수",
            "끝",
            "침체의",
            "주가도",
            "시청하실",
            "반도체",
            "또는",
            "유튜브",
            "게임",
            "시작",
            "탑픽"
        ],
        "아프리카TV": 1,
        "주가": 2,
        "가격": 1,
        "아프리카TV_주가_가격": 4,
        "차트이미지경로": "mksearchimgpath",
        "tvcharturl": "charturl"
    },
    {
        "title": "[김민수의 잠금해제] 세경하이테크 급등, 2024년 폴더블 믿고 주가 우상향?",
        "newstext": "\n\n\n\n잠겨있는 내 계좌의 수익률을 해제하라!\n\n시장이 재평가 중인 시세의 주인공과\n\n앞으로 재평가가 기대되는 시세의 주인공을 한 번에 만날 수 있는 시간.\n\n김민수 레몬리서치 대표가 분석하는 오늘 시장의 주인공은?\n\n\n\n(출연) 김민수 레몬리서치 대표\n\n\n\n1. 분석해서 잠금해제 → 노루페인트\n\n- 업황 위축 vs 가격 인상\n\n- 리모델링· 인테리어 등으로 페인트 수요 증가\n\n- 2차전지 사업 진출… 매출 본격화 기대\n\n- 목표가 12,000원 / 손절가 8,900원\n\n\n\n2. 분석해서 잠금해제 → 세경하이테크\n\n- 2024년 스마트폰 시장 성장세 전망\n\n- 삼성전자 중저가 폴더블 시장 확대\n\n- 3분기 호실적 달성, 4분기도 이어질까?\n\n- 목표가 16,500원 / 손절가 12,000원\n\n\n\n\n\n※ 이 방송은 매일 오전 9시 50분 ~ 10시 50분에 LIVE로 시청하실 수 있습니다.\n\n방송 종료 후에는 유튜브 또는 인터넷 다시보기로 시청하실 수 있습니다.\n\n\n\n시청 방법\n\n▶ 유튜브 MTN 머니투데이방송 공식 채널 (☞ MTN 또는 머니투데이방송 검색)\n\n▶ 케이블TV (Btv 152번, 올레tv 181번, U+tv 163번, 스카이라이프 92번)\n\n▶ WAVE, 카카오TV, NAVER TV, 아프리카TV, ZUM TV\n\n▶ 머니투데이방송 홈페이지\n\n\n\n",
        "summary": "시장이 재평가 중인 시세의 주인공과앞으로 재평가가 기대되는 시세의 주인공을 한 번에 만날 수 있는 시간.\n분석해서 잠금해제 → 노루페인트- 업황 위축 vs 가격 인상- 리모델링· 인테리어 등으로 페인트 수요 증가- 2차전지 사업 진출… 매출 본격화 기대- 목표가 12,000원 / 손절가 8,900원2.\n분석해서 잠금해제 → 세경하이테크- 2024년 스마트폰 시장 성장세 전망- 삼성전자 중저가 폴더블 시장 확대- 3분기 호실적 달성, 4분기도 이어질까?\n- 목표가 16,500원 / 손절가 12,000원※ 이 방송은 매일 오전 9시 50분 ~ 10시 50분에 LIVE로 시청하실 수 있습니다.\n방송 종료 후에는 유튜브 또는 인터넷 다시보기로 시청하실 수 있습니다.",
        "gentime": "2023-11-15T13:17:11.000Z",
        "img": "https://cdn.mtn.co.kr/2023/11/15/20231115_10_01_mns_1.jpg",
        "link": "https://news.mtn.co.kr/news-detail/2023111512575181883",
        "companytag": "none",
        "imagelist": "none",
        "keywords": [
            "세경하이테크",
            "폴더블",
            "잠금해제",
            "분석해서",
            "우상향",
            "시청하실",
            "믿고",
            "김민수의",
            "급등",
            "2024년",
            "수",
            "머니투데이방송",
            "시세의",
            "유튜브",
            "시장",
            "목표가",
            "주가",
            "손절가"
        ],
        "아프리카TV": 1,
        "주가": 0,
        "가격": 1,
        "아프리카TV_주가_가격": 2,
        "차트이미지경로": "mksearchimgpath",
        "tvcharturl": "charturl"
    },
    {
        "title": "[나인원의 내일장 홀인원] 오파스넷 지금의 주가 상승, '테마vs내실 다지기' 무엇일까?",
        "newstext": "\n\n\n\n진행 : 김민지 앵커\n\n출연 : 박재호(나인원) MTN W 어드바이저\n\n\n\n▶ 대량 거래대금 - 두산로보틱스\n\n\n\n\n\n▶▶ 나인원 Pick '오파스넷'\n\n- IT 솔루션 전문기업\n\n- 기업용 시스템 통합·개발 전문\n\n- 중요 지지 가격 16,500원\n\n\n\n\n\n※ 이 방송은 매일 13시 30분 ~ 15시 41분에 LIVE로 시청하실 수 있습니다.\n\n방송 종료 후에는 유튜브 또는 인터넷 다시보기로 시청하실 수 있습니다.\n\n\n\n시청 방법\n\n▶ 유튜브 MTN 머니투데이방송 공식 채널 (☞ MTN 또는 머니투데이방송 검색)\n\n▶ 케이블TV (Btv 152번, 올레tv 181번, U+tv 163번, 스카이라이프 92번)\n\n▶ WAVE, 카카오TV, NAVER TV, 아프리카TV, ZUM TV\n\n▶ 머니투데이방송 홈페이지\n\n",
        "summary": "진행 : 김민지 앵커출연 : 박재호(나인원) MTN W 어드바이저▶ 대량 거래대금 - 두산로보틱스▶▶ 나인원 Pick '오파스넷'- IT 솔루션 전문기업- 기업용 시스템 통합·개발 전문- 중요 지지 가격 16,500원※ 이 방송은 매일 13시 30분 ~ 15시 41분에 LIVE로 시청하실 수 있습니다.\n방송 종료 후에는 유튜브 또는 인터넷 다시보기로 시청하실 수 있습니다.\n시청 방법▶ 유튜브 MTN 머니투데이방송 공식 채널 (☞ MTN 또는 머니투데이방송 검색)▶ 케이블TV (Btv 152번, 올레tv 181번, U+tv 163번, 스카이라이프 92번)▶ WAVE, 카카오TV, NAVER TV, 아프리카TV, ZUM TV▶ 머니투데이방송 홈페이지",
        "gentime": "2023-11-23T16:44:42.000Z",
        "img": "https://cdn.mtn.co.kr/2023/11/23/20231123_closing_08_yyj_1.jpg",
        "link": "https://news.mtn.co.kr/news-detail/2023112316311190571",
        "companytag": "none",
        "imagelist": "none",
        "keywords": [
            "머니투데이방송",
            "홀인원",
            "오파스넷",
            "내일장",
            "후에는",
            "다지기",
            "수",
            "테마vs내실",
            "주가",
            "시청하실",
            "또는",
            "유튜브",
            "통합개발",
            "mtn",
            "무엇일까",
            "홈페이지",
            "지금의",
            "나인원의",
            "상승",
            "tv"
        ],
        "아프리카TV": 1,
        "주가": 0,
        "가격": 1,
        "아프리카TV_주가_가격": 2,
        "차트이미지경로": "mksearchimgpath",
        "tvcharturl": "charturl"
    }
]